showman/__init__.py
showman/__main__.py
showman/common.py
showman/converter.py
showman/executer.py
showman/packager.py
showman/showman.toml
showman/formatter.typ
showman-0.1.2.dist-info/METADATA
showman-0.1.2.dist-info/WHEEL
showman-0.1.2.dist-info/entry_points.txt
showman-0.1.2.dist-info/licenses/LICENSE
showman-0.1.2.dist-info/RECORD
