Metadata-Version: 2.3
Name: showman
Version: 0.1.2
Summary: Eval & show typst code outputs inline with their source
Project-URL: Source, https://github.com/ntjess/showman
Author-email: Nathan Jessurun <ntjessu@gmail.com>
Requires-Python: >=3.9
Requires-Dist: fire
Requires-Dist: omegaconf
Requires-Dist: packaging
Requires-Dist: pexpect
Requires-Dist: pypandoc
Requires-Dist: tomli
